chainmock/__init__.py
chainmock/_api.py
chainmock/_doctest.py
chainmock/_pytest_plugin.py
chainmock/_unittest.py
chainmock/mock.py
chainmock/py.typed
chainmock-1.0.0.dist-info/LICENSE
chainmock-1.0.0.dist-info/METADATA
chainmock-1.0.0.dist-info/WHEEL
chainmock-1.0.0.dist-info/entry_points.txt
chainmock-1.0.0.dist-info/RECORD
