Metadata-Version: 2.1
Name: chainmock
Version: 1.0.0
Summary: Mocking library for Python and Pytest
Home-page: https://github.com/ollipa/chainmock
License: MIT
Keywords: testing,mock,mocking,pytest
Author: Olli Paakkunainen
Author-email: olli@paakkunainen.fi
Requires-Python: >=3.9,<4.0
Classifier: Development Status :: 5 - Production/Stable
Classifier: Framework :: Pytest
Classifier: Intended Audience :: Developers
Classifier: License :: OSI Approved :: MIT License
Classifier: Programming Language :: Python :: 3
Classifier: Programming Language :: Python :: 3.9
Classifier: Programming Language :: Python :: 3.10
Classifier: Programming Language :: Python :: 3.11
Classifier: Programming Language :: Python :: 3.12
Classifier: Programming Language :: Python :: 3.13
Classifier: Programming Language :: Python :: 3 :: Only
Classifier: Programming Language :: Python :: 3.14
Classifier: Programming Language :: Python :: Implementation :: PyPy
Classifier: Topic :: Software Development :: Testing
Classifier: Topic :: Software Development :: Testing :: Mocking
Classifier: Topic :: Software Development :: Testing :: Unit
Classifier: Typing :: Typed
Requires-Dist: typing-extensions (>=3.10.0) ; python_version < "3.10"
Project-URL: Documentation, https://chainmock.readthedocs.io
Project-URL: Issue Tracker, https://github.com/ollipa/chainmock/issues
Project-URL: Repository, https://github.com/ollipa/chainmock
